{
  "project_info": {
    "project_number": "522514873901",
    "project_id": "socialhub-425019",
    "storage_bucket": "socialhub-425019.appspot.com"
  },
  "client": [
    {
      "client_info": {
        "mobilesdk_app_id": "1:522514873901:android:68125908ef62a769d542a4",
        "android_client_info": {
          "package_name": "com.vladima.socialhub"
        }
      },
      "oauth_client": [
        {
          "client_id": "522514873901-678p39059eqv303bnbdp4sclm30838lr.apps.googleusercontent.com",
          "client_type": 3
        }
      ],
      "api_key": [
        {
          "current_key": "AIzaSyCaoYJs3yL-VEvrx7EYyrvcmFrOK_eOBFc"
        }
      ],
      "services": {
        "appinvite_service": {
          "other_platform_oauth_client": [
            {
              "client_id": "522514873901-678p39059eqv303bnbdp4sclm30838lr.apps.googleusercontent.com",
              "client_type": 3
            }
          ]
        }
      }
    }
  ],
  "configuration_version": "1"
}